{
  "project_info": {
    "project_number": "594081514957",
    "project_id": "fruit-hub-fe449",
    "storage_bucket": "fruit-hub-fe449.firebasestorage.app"
  },
  "client": [
    {
      "client_info": {
        "mobilesdk_app_id": "1:594081514957:android:c7a3d8d47e1a0822123084",
        "android_client_info": {
          "package_name": "com.example.fruits_hub"
        }
      },
      "oauth_client": [],
      "api_key": [
        {
          "current_key": "AIzaSyDWuxv-DeD-0llRNFgxSK6mMFdog6DcM6M"
        }
      ],
      "services": {
        "appinvite_service": {
          "other_platform_oauth_client": []
        }
      }
    }
  ],
  "configuration_version": "1"
}